exchange_rate_api_client/__init__.py
exchange_rate_api_client/_client.py
exchange_rate_api_client/_error_handlers.py
exchange_rate_api_client/_open.py
exchange_rate_api_client/commons.py
exchange_rate_api_client/exceptions.py
exchange_rate_api_client-0.1.1.dist-info/LICENSE
exchange_rate_api_client-0.1.1.dist-info/METADATA
exchange_rate_api_client-0.1.1.dist-info/WHEEL
exchange_rate_api_client-0.1.1.dist-info/top_level.txt
exchange_rate_api_client-0.1.1.dist-info/RECORD
