Metadata-Version: 2.2
Name: exchange-rate-api-client
Version: 0.1.1
Summary: Unofficial client to interact with the Exchange Rate API V6
Home-page: https://github.com/dfm18/exchange-rate-api-client
Author: Daniel Fortich
Author-email: fortichdaniel16@gmail.com
Classifier: Programming Language :: Python :: 3
Classifier: License :: OSI Approved :: MIT License
Classifier: Operating System :: OS Independent
Requires-Python: >=3.8
License-File: LICENSE
Requires-Dist: requests>=2.32
Requires-Dist: pydantic>=2.10
Dynamic: author
Dynamic: author-email
Dynamic: classifier
Dynamic: description
Dynamic: description-content-type
Dynamic: home-page
Dynamic: requires-dist
Dynamic: requires-python
Dynamic: summary
